zoomdotpy/__init__.py
zoomdotpy/client.py
zoomdotpy/api/__init__.py
zoomdotpy/api/base.py
zoomdotpy/api/meetings.py
zoomdotpy/api/rooms.py
zoomdotpy/api/phones/__init__.py
zoomdotpy/api/phones/audios.py
zoomdotpy/api/phones/auto_receptionists.py
zoomdotpy/api/phones/batch_locations.py
zoomdotpy/api/phones/billing_accounts.py
zoomdotpy/api/phones/blocked_list.py
zoomdotpy/api/phones/byoc_numbers.py
zoomdotpy/api/phones/call_logs.py
zoomdotpy/api/phones/call_queues.py
zoomdotpy/api/phones/calling_plans.py
zoomdotpy/api/phones/carrier_peering.py
zoomdotpy/api/phones/carrier_reseller.py
zoomdotpy/api/phones/common_area_phones.py
zoomdotpy/api/phones/common_areas.py
zoomdotpy/api/phones/company_number.py
zoomdotpy/api/phones/devices.py
zoomdotpy/api/phones/dial_by_name_directory.py
zoomdotpy/api/phones/emergency_addresses.py
zoomdotpy/api/phones/emergency_number_pools.py
zoomdotpy/api/phones/extension.py
zoomdotpy/api/phones/external_contacts.py
zoomdotpy/api/phones/firmware_update_rules.py
zoomdotpy/api/phones/firmwares.py
zoomdotpy/api/phones/group_call_pickup.py
zoomdotpy/api/phones/locations.py
zoomdotpy/api/phones/metrics.py
zoomdotpy/api/phones/monitoring_groups.py
zoomdotpy/api/phones/numbers.py
zoomdotpy/api/phones/outbound_caller_id.py
zoomdotpy/api/phones/peering.py
zoomdotpy/api/phones/plans.py
zoomdotpy/api/phones/ported_numbers.py
zoomdotpy/api/phones/provision_templates.py
zoomdotpy/api/phones/recording_transcript.py
zoomdotpy/api/phones/recordings.py
zoomdotpy/api/phones/reports.py
zoomdotpy/api/phones/roles.py
zoomdotpy/api/phones/rooms.py
zoomdotpy/api/phones/routing_rules.py
zoomdotpy/api/phones/setting_templates.py
zoomdotpy/api/phones/settings.py
zoomdotpy/api/phones/shared_line_appearances.py
zoomdotpy/api/phones/shared_line_groups.py
zoomdotpy/api/phones/sip_groups.py
zoomdotpy/api/phones/sip_trunk.py
zoomdotpy/api/phones/site_settings.py
zoomdotpy/api/phones/sites.py
zoomdotpy/api/phones/sms.py
zoomdotpy/api/phones/sms_campaigns.py
zoomdotpy-0.1.11.dist-info/LICENSE
zoomdotpy-0.1.11.dist-info/METADATA
zoomdotpy-0.1.11.dist-info/WHEEL
zoomdotpy-0.1.11.dist-info/top_level.txt
zoomdotpy-0.1.11.dist-info/RECORD
