Metadata-Version: 2.1
Name: zoomdotpy
Version: 0.1.11
License-File: LICENSE
Requires-Dist: requests
